dictionary/__init__.py
dictionary/dictionary.py
yahya_cs453_assignment1_v2-2.0.0.dist-info/METADATA
yahya_cs453_assignment1_v2-2.0.0.dist-info/WHEEL
yahya_cs453_assignment1_v2-2.0.0.dist-info/top_level.txt
yahya_cs453_assignment1_v2-2.0.0.dist-info/RECORD
