Metadata-Version: 2.1
Name: yahya-cs453-assignment1-v2
Version: 2.0.0
Summary: UNKNOWN
Author: Yahya Mohamed
License: UNKNOWN
Platform: UNKNOWN
Requires-Python: >=3.8
Requires-Dist: requests (>=2.23.0)
